mm_dev/__init__.py
mm_dev/_common.py
mm_dev/backup_projects_dir.py
mm_dev/dec2hex.py
mm_dev/dh.py
mm_dev/g.py
mm_dev/h.py
mm_dev/hex2dec.py
mm_dev/myip.py
mm_dev/p.py
mm_dev/proxy_check.py
mm_dev/random.py
mm_dev-0.0.11.dist-info/METADATA
mm_dev-0.0.11.dist-info/WHEEL
mm_dev-0.0.11.dist-info/entry_points.txt
mm_dev-0.0.11.dist-info/RECORD
