Metadata-Version: 2.4
Name: mm-dev
Version: 0.0.11
Requires-Python: >=3.12
Requires-Dist: mm-std>=0.3.26
Requires-Dist: packaging>=24.2
Requires-Dist: typer~=0.14.0
